{
  "bryanReynolds": {
    "name": "Bryan",
    "lastName": "Reynolds",
    "userName": "bryanReynolds"
  },
  "davidReynolds": {
    "name": "David",
    "lastName": "Reynolds",
    "userName": "davidReynolds"
  },
  "lyndaReynolds": {
    "name": "Lynda",
    "lastName": "Reynolds",
    "userName": "lyndaReynolds"
  },
  "hectorMoreno": {
    "name": "Dallas",
    "lastName": "Wind",
    "userName": "hectorMoreno"
  },
  "jackMoreno": {
    "name": "Jack",
    "lastName": "Moreno",
    "userName": "jackMoreno"
  }
}
